<?xml version="1.0" encoding="UTF-8"?>
<objects serializationModel="Studio.02.00.00">
	<object class="AudioFile" id="{9a151015-9a4e-4a1d-82dc-33edf7e7416e}">
		<property name="assetPath">
			<value>BulletBag03.ogg</value>
		</property>
		<property name="frequencyInKHz">
			<value>96</value>
		</property>
		<property name="channelCount">
			<value>2</value>
		</property>
		<property name="length">
			<value>0.80000000000000004</value>
		</property>
		<relationship name="masterAssetFolder">
			<destination>{06008a69-d7ce-414f-ad87-5f47e1c3988d}</destination>
		</relationship>
	</object>
</objects>
