<?xml version="1.0" encoding="UTF-8"?>
<objects serializationModel="Studio.02.00.00">
	<object class="AudioFile" id="{a1d90db4-22b9-4189-a6c5-020abe7c0b14}">
		<property name="assetPath">
			<value>29-Foley Taps - 05-1911-pistol-foley-taps-3.wav</value>
		</property>
		<property name="frequencyInKHz">
			<value>96</value>
		</property>
		<property name="channelCount">
			<value>2</value>
		</property>
		<property name="length">
			<value>0.23033333333333333</value>
		</property>
		<relationship name="masterAssetFolder">
			<destination>{06008a69-d7ce-414f-ad87-5f47e1c3988d}</destination>
		</relationship>
	</object>
</objects>
